rust_docs_scraper/__init__.py
rust_docs_scraper/rust_docs_scraper.py
rust_docs_scraper-0.0.1.dist-info/LICENSE
rust_docs_scraper-0.0.1.dist-info/METADATA
rust_docs_scraper-0.0.1.dist-info/WHEEL
rust_docs_scraper-0.0.1.dist-info/entry_points.txt
rust_docs_scraper-0.0.1.dist-info/RECORD
