Metadata-Version: 2.1
Name: rust_docs_scraper
Version: 0.0.1
Summary: A Multithreaded Rust / Web-Based HTML Documentation Scraper and Formatter
License: MIT
Author: Ben Gorlick
Author-email: ben@unifiedlearning.ai
Requires-Python: >=3.6,<4.0
Classifier: License :: OSI Approved :: MIT License
Classifier: Programming Language :: Python :: 3
Classifier: Programming Language :: Python :: 3.6
Classifier: Programming Language :: Python :: 3.7
Classifier: Programming Language :: Python :: 3.8
Classifier: Programming Language :: Python :: 3.9
Classifier: Programming Language :: Python :: 3.10
Classifier: Programming Language :: Python :: 3.11
Classifier: Programming Language :: Python :: 3.12
Requires-Dist: beautifulsoup4 (>=4.12.3,<5.0.0)
Requires-Dist: colorama (>=0.4.6,<0.5.0)
Requires-Dist: requests (>=2.31.0,<3.0.0)
Requires-Dist: semver (>=3.0.2,<4.0.0)
